pybandits/__init__.py
pybandits/actions_manager.py
pybandits/base.py
pybandits/base_model.py
pybandits/cmab.py
pybandits/cmab_simulator.py
pybandits/mab.py
pybandits/model.py
pybandits/offline_policy_estimator.py
pybandits/offline_policy_evaluator.py
pybandits/pydantic_version_compatibility.py
pybandits/quantitative_model.py
pybandits/simulator.py
pybandits/smab.py
pybandits/smab_simulator.py
pybandits/strategy.py
pybandits/utils.py
pybandits-4.0.17.dist-info/METADATA
pybandits-4.0.17.dist-info/WHEEL
pybandits-4.0.17.dist-info/licenses/LICENSE
pybandits-4.0.17.dist-info/RECORD
