Metadata-Version: 2.4
Name: pybandits
Version: 4.0.17
Summary: Python Multi-Armed Bandit Library
License: MIT
License-File: LICENSE
Keywords: multi-armed bandits,reinforcement-learning,optimization
Author: Dario d'Andrea
Author-email: dariod@playtika.com
Requires-Python: >=3.9,<3.13
Classifier: License :: OSI Approved :: MIT License
Classifier: Programming Language :: Python :: 3
Classifier: Programming Language :: Python :: 3.9
Classifier: Programming Language :: Python :: 3.10
Classifier: Programming Language :: Python :: 3.11
Classifier: Programming Language :: Python :: 3.12
Requires-Dist: bokeh (>=3.1,<4.0)
Requires-Dist: loguru (>=0.6,<0.7)
Requires-Dist: numpy (>=1.25) ; python_version >= "3.9" and python_version < "3.12"
Requires-Dist: numpy (>=1.26) ; python_version == "3.12"
Requires-Dist: optuna (>=3.6,<4.0)
Requires-Dist: pydantic (>=1.10,<3)
Requires-Dist: pymc (>=5.10,<6.0) ; python_version >= "3.9"
Requires-Dist: pymc (>=5.3,<6.0) ; python_version == "3.8"
Requires-Dist: scikit-learn (>=1.1,<2.0)
Requires-Dist: scipy (>=1.11,<1.13) ; python_version == "3.12"
Requires-Dist: scipy (>=1.9,<1.13) ; python_version >= "3.8" and python_version < "3.12"
Project-URL: Homepage, https://github.com/PlaytikaOSS/pybandits
Project-URL: Repository, https://github.com/PlaytikaOSS/pybandits
